[
  {
    "name": "populer",
    "address": "চৌমুহনী বাজার, চাতরী, আনোয়ারা, চট্টগ্রাম",
    "phone 1": "01865232311",
    "phone 2":"01755666941",
    "phone 3":"01755666942",
    "phone 4":"01847135472",
    
    "dcotors": [
      {
        "name": "ডাঃ মোঃ মিজানুর রহমান (মিজান)",
        "spacalist": "হাড়-ভাঙ্গা, বাত-ব্যথা, মেরুদন্ড ব্যথা ও হাড় জোড়া রোগ চিকিৎসক",
        "degree": "এম.বি.বি.এস. (সি ইউ) এফ.সি.পি.এস (অর্থোপেডিক্স সার্জারী) পার্ট-২ এম. পি.এইচ (কোর্স) ",
        "post":"চট্টগ্রাম মেডিকেল কলেজ হাসপাতাল",
        "time": "প্রতি রবি ও মঙ্গলবার বিকাল ৩টা সন্ধ্যা ৬টা শুক্রবার সকাল ১০টা-১২টা পর্যন্ত।"
      },
      {
        "name": "ডাঃ প্রভা মজুমদার",
        "spacalist": "প্রসূতি, স্ত্রী রোগ বিশেষজ্ঞ ও সার্জন",
        "degree": "এম.বি.বি.এস. এফ.সি.পি.এস. (অবস্ এন্ড গাইনী) (পার্ট-২)",
        "post":"",
        "time": " সাক্ষাতের সময় প্রতি শনি, সোম ও বুধবার বিকাল ৩টা ৬টা"
      },
      {
        "name": "ডাঃ মোহাম্মদ এহ্সানার",
        "spacalist": "চর্ম, যৌন এলার্জি, নখ, চুলরোগ বিশেষজ্ঞ ও কসমেটিক লেজার সার্জন",
        "degree": "এম.বি.বি.এস (ঢাকা),ডি.ডি (থাইল্যান্ড এন্ড জাপান), ডি.পি.ডি (লন্ডন). চীন এন্ড লেজার সার্জন (ব্যাংক), এ.বি.এল.এস (আমেরিকা))",
        "post":"",
        "time": " প্রতি শনিবার সকাল ১০টা-১২টা- পর্যন্ত "
      },
      {
        "name": "ডাঃ প্রণবাশীষ দত্ত",
        "spacalist": "এম.বি.বি.এস. এফ.সি.পি.এস.(শিশু স্বাস্থ্য শেষ পর্ব) ডি.সি.এইচ. পি.জি.টি",
        "degree": "এম.বি.বি.এস (ঢাকা),ডি.ডি (থাইল্যান্ড এন্ড জাপান), ডি.পি.ডি (লন্ডন). চীন এন্ড লেজার সার্জন (ব্যাংক), এ.বি.এল.এস (আমেরিকা))",
        "post":"",
        "time": " সাক্ষাতের সময় রবি, সোম, মঙ্গল, বুধ, বৃহস্পতিয বিকাল ২টা-৬টা পর্যন্ত "
      },
      {
        "name": "ডাঃ আব্দুল মন্নানষত্ত",
        "spacalist": "মেডিসিন, হৃদরোগ, চর্ম ও যৌনরোগ মহিলা ও শিশুরোগ অভিজ্ঞ",
         "degree": "এম.বি.বি.এস, বি. সি. এস (স্বাস্থ্য) মেডিসিন, কার্ডিওলজি বিষয়ে স্নাতকোত্তর প্রশিক্ষণপ্রাপ্ত",
        "post":"",
        "time": "সাক্ষাতের সময় প্রতি শনি, রবি, মঙ্গল ও বুধবার বিকাল ৪টা ৭টা পর্যন্ত"
      },
      {
        "name": "ডাঃ আব্দুল মন্নান",
        "spacalist": "মেডিসিন, হৃদরোগ, চর্ম ও যৌনরোগ মহিলা ও শিশুরোগ অভিজ্ঞ",
        "degree": "  এম.বি.বি.এস, বি. সি. এস (স্বাস্থ্য) মেডিসিন, কার্ডিওলজি বিষয়ে স্নাতকোত্তর প্রশিক্ষণপ্রাপ্ত", 
        "post":"",
        "time": "সাক্ষাতের সময় প্রতি শনি, রবি, মঙ্গল ও বুধবার বিকাল ৪টা ৭টা পর্যন্ত"
      },
      {
        "name": "ডাঃ লক্ষ্মী পদ",
        "spacalist": "হৃদরোগ, বাতজ্বর ও উচ্চ রক্তচাপ বিশেষজ্ঞ",
        "degree": "হৃদরোগ, বাতজ্বর ও উচ্চ রক্তচাপ বিশেষজ্ঞ এম.বি.বি.এস. ডি. কার্ড (বি.এস. এম.এম.ইউ) পি.জি.টি (মেডিসিন, নেফ্রোলজি), (কনসালটেন্ট, কার্ডিওলজি)",
        "post":"",
        "time": "সাক্ষাতের সময় প্রতি সোম ও বুধবার দুপুর ৩টা থেকে বিকাল ৫টা পর্যন্ত"
      },
      {
        "name": "ডাঃ মোহাম্মদ শাহীন চৌধুরী",
        "spacalist": "মেডিসিন, ডায়াবেটিস, শিশু রোগ ও আল্ট্রাসনোগ্রাফী",
        "degree": "এম.বি.বি.এস. (চ.মে.ক), সি.সি.ডি (বারডেম) বি.সি.এস (স্বাস্থ্য), সি.এম.ইউ, (ঢাবি)",
        "post":"",
        "time": "প্রতি রবি ও মঙ্গলবার বিকাল ৩টা - ৬টা পর্যন্ত পর্যন্ত"
      },
      {
        "name": "ডাঃ বাসু দেব দে",
        "spacalist": "নাক, কান ও গলা রোগ বিশেষজ্ঞ ও সার্জন",
        "degree": "এম.বি.বি.এস (ঢাকা). পি.জি.টি. সি.সি.ডি (বারডেম),ডি.এল. ও",
        "post":"",
        "time": "সাক্ষাতের সময়প্রতি মঙ্গলবার দুপর ২টা - ৩.৩০টাত পর্যন্ত"
      },
      {
        "name": "ডাঃ সালমা আকতার সমরজিত মল্লিক",
        "spacalist": "প্রসূতি ও স্ত্রী রোগ বিশেষজ্ঞ ও সার্জনন",
        "degree": "নাক, কান ও গলা রোগ বিশেষজ্ঞ ও সার্জ",
        "post":"",
        "time": "প্রতি রবি মঙ্গলবার বিকাল ৩টা স শুক্রবার সকাল ১০টা ১টা পর্যন্ত"
      },
      {
        "name": "ডাঃ সালমা আকতার সমরজিত মল্লিক",
        "spacalist": "প্রসূতি ও স্ত্রী রোগ বিশেষজ্ঞ ও সার্জনন",
        "degree": "নাক, কান ও গলা রোগ বিশেষজ্ঞ ও সার্জ",
        "post":"",
        "time": "প্রতি রবি মঙ্গলবার বিকাল ৩টা স শুক্রবার সকাল ১০টা ১টা পর্যন্ত"
      },
      {
        "name": "সমরজিত মল্লিক",
        "spacalist": "মেডিসিন, থাইরয়েড, ডায়াবেটিস হরমোন ও এলার্জি রোগে অভিজ্ঞ",
        "degree": "এম.বি.বি.এস. পি.জি.টি (মেডিসিন) এফ.সি.পি.এস (এন্ডোক্রাইনোলজি) দ্বিতীয় পর্ব।",
        "post":"",
        "time": "পশি, সোম ও বুধবার বিকাল ৩টা - ৫টা পর্যন্ত পর্যন্ত"
      }
    ]
  }, {
    "name": "শেভরণ ক্লিনিক্যাল ল্যাবরেটরী (প্রাঃ) লিমিটেড আনোয়ারা শাখা",
    "address": "চৌমুহনী বাজার, চাতরী, আনোয়ারা, চট্টগ্রাম",
    "phone 1": "01847135470",
    "phone 2":"01755666941",
    "phone 3":"01755666942",
    "phone 4":"01847135472",
    "dcotors": [
         {
        "name": "ডাঃ সুমনা সরকার ",
        "spacalist": " চক্ষুরোগ বিশেষজ্ঞ ও সার্জন",
        "degree": "এমবিবিএস,বিসিএস (স্বাস্থ্য) ডিসিও ফেলো মেডিকেল রেটিনা কনসালটেন্ট",  
        "post":"কনসালটেন্ট শেভরণ আই রিসার্চ সেন্টার আনোয়ারা শাখা",
        "time": "প্রতি শনিবার ও বুধবার (বিকাল) বিকাল"
      },{
        "name": "ডাঃ কামরুন নেছা বেগম (রোজী)",
        "spacalist": "প্রসূতী ও স্ত্রীরোগ বিভাগ",
        "degree": "এমবিবিএস, বিসিএস (স্বাস্থ্য), এফসিপিএস (গাইনী), এমএস (থিসিস)",
        "post":"সহযোগী অধ্যাপক চট্টগ্রাম মেডিকেল কলেজ হাসপাতাল প্রসূতী, স্ত্রীরোগ বিশেষজ্ঞ ও সার্জন",
        "time": "প্রতি শনিবার ও বুধবার (বিকাল) বিকাল"
      },{
        "name": "ডাঃ সনজয় দে",
        "spacalist": "লিভার বিভাগ",
        "degree": "এমবিবিএস, এমডি (হেপাটোলজি)",
        "post":"চট্টগ্রাম মেডিকেল কলেজ হাসপাতাল লিভার রোগ বিশেষজ্ঞ",
        "time": "প্রতি শুক্রবার (বিকাল)"
      },{
        "name": "ডাঃ খালেদ ইবনে আনোয়ার",
        "spacalist": "সার্জন অর্থোপেডিক্স ও ট্রমাটলোজী বিভাগ",
        "degree": "এমবিবিএস, বিসিএস (স্বাস্থ্য), ডি-অর্থো (বিএসএমএমইউ) এও, ট্রমা ফেলো (থাইল্যান্ড)এও ট্রমা বেসিক, এডভান্স এন্ড মাস্টার্স",
        "post":"চট্টগ্রাম মেডিকেল কলেজ হাসপাতাল সিনিয়র কনসালটেন্ট ও ট্রমা",
        "time": "প্রতি বৃহস্পতিবার (বিকাল)"
      },{
        "name": "ডাঃ ইফতেখার আহমেদ",
        "spacalist": "অর্থোপেডিক এন্ড ট্রমা সার্জন",
        "degree": "এমবিবিএস, বিসিএস (স্বাস্থ্য), এমএস (অর্থোপেডিক সার্জারী)",
        "post":"(নিটোর/প্রাক্তন পঙ্গু হাসপাতাল) কনসালটেন্ট (অর্থোপেডিক সার্জারী)",
        "time": "প্রতি শুক্রবার (বিকাল)"
      },{
        "name": "ডাঃ শাহ্জামান মনছুর খান",
        "spacalist": "চর্ম, যৌন, কসমেটিক ও এলার্জি রোগ বিশেষজ্ঞ",
        "degree": "এমবিবিএস, ডিডিভি (চর্ম ও যৌন) ",
        "post":"এক্স সিনিয়র কনসালটেন্ট ও বিভাগীয় প্রধান চট্টগ্রাম ডায়াবেটিক জেনারেল হাসপাতাল",
        "time": "প্রতি শুক্রবার (সকাল)"
      },{
        "name": "ডাঃ মোঃ সাইফ উদ্দীন আজাদ",
        "spacalist": "স্ট্রোক, প্যারালাইসিস, মগীরোগ, মাথা ব্যথা, কোমর ব্যথা,ঘাড় ব্যথা সহ সকল স্নায়ু রোগ বিশেষজ্ঞ",
        "degree": "এমবিবিএস (সিইউ), সিসিডি (বারডেম), ডি-কার্ড (বিএসএমএমইউ), এমসিপিএস (মেডিসিন) এফসিপিএস (মেডিসিন-শেষপর্ব)",
        "post":"সহকারী অধ্যাপক, চট্টগ্রাম মা ও শিশু হাসপাতাল মেডিকেল কলেজ, আগ্রাবাদ",
        "time": "প্রতি রবিবার (বিকাল)"
      },{
        "name": "ডাঃ মোহাম্মদ সাইফুল্লাহ চৌধুর",
        "spacalist": "ডায়াবেটিস, থাইরয়েড, মেডিসিন ও হরমোন রোগ বিশেষজ্ঞ",
        "degree": "এমবিবিএস, বিসিএস (স্বাস্থ্য),এফসিপিএস (মেডিসিন পার্ট-২) ডিইএম (বারডেম)",
        "post":"এন্ডোক্রাইনোলজিস্ট চট্টগ্রাম মেডিকেল কলেজ হাসপাতাল",
        "time": "প্রতি সোমবার (বিকাল)"
      },{
        "name": "ডাঃ জিনাত সুলতানা শারমিন",
        "spacalist": "শিশু, শিশুপুষ্টি, লিভার ও পরিপাকতন্ত্র বিশেষজ্ঞ",
        "degree": "এমডি (শিশু গ্যাস্ট্রোএন্টেরোলজি এন্ড নিউট্রিশন) বিএসএমএমইউ, ঢাকা",
        "post":"এক্স-ক্লিনিক্যাল ফেলো ইন আইসিডিডিআরবি (ঢাকা)",
        "time": "প্রতি রবিবার (বিকাল) "
      },
      {
        "name": "ডাঃ সাগর দেব (তপু)",
        "spacalist": "ইনফার্টিলিটি (বন্ধ্যাত্ব) বিষয়ে বিশেষ প্রশিক্ষন প্রাপ্ত (বেঙ্গালুরু, ভারত) ) প্রসূতী স্ত্রী (মহিলা) ও বন্ধ্যাত্ব রোগ বিশেষজ্ঞ ও সার্জন",
        "degree": "এমবিবিএস, বিসিএস (স্বাস্থ্য),এমডি (নিউরোমেডিসিন)",
        "post":"কনসালটেন্ট - নিউরোলজি চট্টগ্রাম মেডিকেল কলেজ হাসপাতাল",
        "time": " প্রতি রবিবার (বিকাল) "
      },
    {
        "name": "ডাঃ ফারাহনাজ মাবুদ সিলভী",
        "spacalist": "ইনফার্টিলিটি (বন্ধ্যাত্ব) বিষয়ে বিশেষ প্রশিক্ষন প্রাপ্ত (বেঙ্গালুরু, ভারত) ) প্রসূতী স্ত্রী (মহিলা) ও বন্ধ্যাত্ব রোগ বিশেষজ্ঞ ও সার্জন",
        "degree": "এমবিবিএস, এমসিপিএস, এমএস (গাইনী",
        "post":"হকারী অধ্যাপক-চট্টগ্রাম মা ও শিশু জেনারেল হাসপাতাল",
        "time": "প্রতি সোমবার (বিকাল)"
      },
          {
        "name": " ডাঃ পার্থ সারথি সরকার",
        "spacalist": "বাত ব্যথা, হরমোন, ডায়াবেটিস, স্ট্রোক ও মেডিসিন বিশেষজ্ঞ",
        "degree": "এমবিবিএস, (ডিএমসি), বিসিএস (স্বাস্থ্য), এমসিপিএস (মেডিসিন), এফসিপিএস (মেডিসিন)",
        "post":"কনসালটেন্ট - মেডিসিন,এক্স কনসালটেন্ট - ঢাকা মেডিকেল কলেজ হাসপাতাল",
        "time": "প্রতি সোমবার ও মঙ্গলবার"
      },{
        "name": "ডাঃ নাসিমা বেগম",
        "spacalist": "প্রসূতী, স্ত্রীরোগ বিশেষজ্ঞ ও সার্জন",
        "degree": "এমবিবিএস, বিসিএস (স্বাস্থ্য), এমএস (গাইনী)",
        "post":"সহযোগী অধ্যাপক-চট্টগ্রাম মেডিকেল কলেজ হাসপাতাল",
        "time": "প্রতি রবিবার ও বৃহস্পতিবার (বিকাল)"
      },{
        "name": "ডাঃ আব্দুল্লাহ আবু সাঈদ",
        "spacalist": "ইন্টারনাল মেডিসিন ও ডায়াবেটিস বিশেষজ্ঞ",
        "degree": "এমবিবিএস, এমডি (ইন্টারনাল মেডিসিন) ফেলো ডায়াবেটোলজী (বারডেম)",
        "post":"সহকারী অধ্যাপক-চট্টগ্রাম মেডিকেল কলেজ হাসপাতাল",
        "time": "প্রতি মঙ্গলবার (বিকাল)"
      },{
        "name": "ডাঃ শাহেদা আকতার রোজী",
        "spacalist": "প্রসূতী, স্ত্রীরোগ বিশেষজ্ঞ ও সার্জন",
        "degree": "এমবিবিএস, বিসিএস (স্বাস্থ্য) এফসিপিএস (গাইনী এন্ড অবস) ",
        "post":"চট্টগ্রাম মেডিকেল কলেজ হাসপাতাল",
        "time": "প্রতি শনিবার ও মঙ্গলবার (বিকাল)"
      },{
        "name": "ডাঃ মোঃ জাবের আবেদীন",
        "spacalist": "বাত ব্যথা, হরমোন, ডায়াবেটিস, স্ট্রোক ও মেডিসিন বিশেষজ্ঞ",
        "degree": "এমবিবিএস, এমডি (ইন্টারনাল মেডিসিন) কনসালটেন্ট - মেডিসিন ",
        "post":"কনসালটেন্ট - মেডিসিন \n চট্টগ্রাম মেডিকেল কলেজ হাসপাতাল",
        "time": "প্রতি শনিবার ও মঙ্গলবার (বিকাল)"
      },{
        "name": "ডাঃ খোরশেদা শিরীন",
        "spacalist": "প্রসূতী, স্ত্রীরোগ বিশেষজ্ঞ ও সার্জন",
        "degree": "এমবিবিএস, বিসিএস (স্বাস্থ্য)",
        "post":"উপ-পরিচালক (স্বাস্থ্য)- চট্টগ্রাম বিভাগ",
        "time": "প্রতি শনিবার ও মঙ্গলবার (বিকাল)"
      },{
        "name": "ডাঃ কিশোর মহাজন",
        "spacalist": "মেডিসিন, বাত ব্যথা (হাটু, ঘাড়, কোমর ব্যথা), প্যারালাসিস, স্ট্রোক, রিজেনারেটিভ মেডিসিন ও পেইন বিশেষজ্ঞ",
        "degree": "এমবিবিএস, এমডি (বিএসএমএমইউ),সিসিডি (বারডেম), ডিপিটি (আয়ারল্যান্ড) ট্রেইন্ড ইন মাস্কুলোস্কেলেটাল আল্ট্রাসাউন্ডক্লিনিক্যাল এন্ড ইন্টারভেনশাল ফিজিয়াট্রিস্ট",
        "post":"সহকারী অধ্যাপক-শিশু স্বাস্থ্য বিভাগ চট্টগ্রাম মা ও শিশু হাসপাতাল মেডিকেল কলেজ ",
        "time": "প্রতি মঙ্গলবার ও শুক্রবার"
      },{
        "name": "ডাঃ কামাল হোসেন (জুয়েল) ",
        "spacalist": "মেডিসিন, বাত ব্যথা (হাটু, ঘাড়, কোমর ব্যথা), প্যারালাসিস, স্ট্রোক, রিজেনারেটিভ মেডিসিন ও পেইন বিশেষজ্ঞ",
        "degree": "এমবিবিএস, ডিসিএইচ",
        "post":"সহকারী অধ্যাপক-শিশু স্বাস্থ্য বিভাগ চট্টগ্রাম মা ও শিশু হাসপাতাল মেডিকেল কলেজ ",
        "time": "প্রতি মঙ্গলবার ও শুক্রবার"
      },{
        "name": "ডাঃ হাশমত আলী মিয়া",
        "spacalist": "পাইলস, হার্নিয়া, পিওথলির পাথর, কিডনী পাথর, বার্ন ও প্লাস্টিক সার্জারীতে অভিজ্ঞ",
        "degree": "এমবিবিএস, বিসিএস (স্বাস্থ্য), এফসিপিএস (সার্জারী) পিজিটি (অর্থোসার্জারী), পিজিটি (বার্ন ও প্লাস্টিক সার্জারী) এফসিপিএস (সার্জারী)- শেষপর্ব, এমএস (থিসিস) ইউরোলজি ",
        "post":"চট্টগ্রাম মেডিকেল কলেজ হাসপাতাল",
        "time": "প্রতি শুক্রবার (সকাল) সোমবার (বিকাল)"
      },{
        "name": " ডাঃ বিলকিস আকতার",
        "spacalist": "ট্রমা (এক্সিডেন্ট) ও মাইক্রোভাস্কুলার সার্জন",
        "degree": "এমবিবিএস, এমএস (অর্থোপেডিক সার্জারী) ",
        "post":"ট্রমা (এক্সিডেন্ট) ও মাইক্রো ভাসকুলার সার্জন (হাত ও পায়ের) চট্টগ্রাম মা ও শিশু জেনারেল হাসপাতাল",
        "time": "প্রতি রবিবার ( বিকাল )"
      },{
        "name": "ডাঃ কাজী শামীম আল মামুন",
        "spacalist": "মেডিসিন ও বাতজ্বর বিশেষজ্ঞ",
        "degree": "এমবিবিএস, বিসিএস (স্বাস্থ্য), এমডি (কার্ডিওলজি) কনসালটেন্ট এন্ড কার্ডিওলজিস্ট",
        "post":"চট্টগ্রাম মেডিকেল কলেজ হাসপাতাল হৃদরোগ",
        "time": "প্রতি রবিবার ও বুধবার"
      },{
        "name": "ডাঃ উমা দেব",
        "spacalist": "প্রসূতী, স্ত্রীরোগ এবং চর্ম রোগ",
        "degree": "এমবিবিএস (চমেক), এফসিপিএস (গাইনী এন্ড অবস)",
        "post":"সহকারী অধ্যাপক বিজিসি ট্রাস্ট মেডিকেল কলেজ",
        "time":"প্রতি বুধবার (বিকাল)"
      },{
        "name": "ডাঃ পারিজাত বিশ্বাস",
        "spacalist": "বাত ব্যাথা, হরমোন, ডায়াবেটিস, স্ট্রোক ও মেডিসিন বিশেষজ্ঞ",
        "degree": "এমবিবিএস (চমেক), বিসিএস (স্বাস্থ্য), এফসিপিএস (মেডিসিন), এমসিপিএস (মেডিসিন) কনসালটেন্ট - (মেডিসিন)",
        "post":"চট্টগ্রাম মেডিকেল কলেজ হাসপাতাল",
        "time": "প্রতি বুধবার ও শুক্রবার (বিকাল)"
      },{
        "name": "ডাঃ মোঃ আরিফুল ইসলাম",
        "spacalist": "মেডিসিন, বাত ব্যথা, হৃদরোগ-শ্বাসকষ্ট অভিজ্ঞ ও ডায়াবেটিস বিশেষজ্ঞ",
        "degree": "এমবিবিএস (সিইউ), বিসিএস (স্বাস্থ্য), এফসিপিএস (মেডিসিনঃ শেষ পর্ব) সিসিডি স্পেশ্যালাইজড ট্রেনিং ইন কার্ডিয়াক ইমার্জেন্সী (এএইচএ)",
        "post":"চট্টগ্রাম মেডিকেল কলেজ হাসপাতাল",
        "time": "প্রতি সোমবার বুধবার ও শুক্রবার"
      },{
        "name": "ডাঃ মোঃ ওমর ফারুক (তুহিন)",
        "spacalist": "কলোরেক্টাল, এন্ডো-ল্যাপারস্কপিক ও লেজার সার্জন",
        "degree": "এমবিবিএস, বিসিএস (স্বাস্থ্য), এফসিপিএস (সার্জারী) এফসিএস (আমেরিকা), ইএফআইএজিইএস (ভারত) ",
        "post":"সহকারী অধ্যাপক চট্টগ্রাম মেডিকেল কলেজ হাসপাতাল জেনারেল",
        "time": "প্রতি বুধবার (বিকাল)"
      },{
        "name": "ডাঃ পম্পি সরকার",
        "spacalist": "নবজাতক ও শিশুরোগ বিশেষজ্ঞ",
        "degree": "এমবিবিএস (সিইউ) ডিসিএইচ (বিএসএমএমইউ)",
        "post":"কনসালটেন্ট চট্টগ্রাম মা ও শিশু হাসপাতাল মেডিকেল কলেজ",
        "time": "প্রতি বুধবার"
      },{
        "name": "ডাঃ সুমন সরকার",
        "spacalist": "বাত ব্যাথা, হরমোন, ডায়াবেটিস, স্ট্রোক ও মেডিসিন বিশেষজ্ঞ",
        "degree": "এমবিবিএস, বিসিএস (স্বাস্থ্য), এফসিপিএস (মেডিসিন)",
        "post":"সহকারী অধ্যাপক - (মেডিসিন) চট্টগ্রাম মেডিকেল কলেজ হাসপাতাল",
        "time": "প্প্রতি শনিবার, সোমবার ও বুধবার"
      },{
        "name": "ডাঃ ফারজানা আখতার (বীথি)",
        "spacalist": "প্রসূতী, স্ত্রীরোগ বিশেষজ্ঞ ও সার্জন",
        "degree": "এমবিবিএস, বিসিএস (স্বাস্থ্য) এফসিপিএস (গাইনী এন্ড অবস)",
        "post":"চট্টগ্রাম মেডিকেল কলেজ হাসপাতাল ",
        "time": "প্রতি রবিবার ও শুক্রবার (বিকাল)"
      },{
        "name": "ডাঃ মনজুরুল কাদের চৌধুরী ",
        "spacalist": "স্ট্রোক, প্যারালাইসিস মৃগীরোগ, মাথা ব্যথা, কোমর ব্যথা, ঘাড় ব্যথা সহ সকল স্নায়ু রোগ বিশেষজ্ঞ",
        "degree": "এমবিবিএস, বিসিএস (স্বাস্থ্য), এমডি (নিউরোমেডিসিন)",
        "post":"সহকারী অধ্যাপক -চট্টগ্রাম মেডিকেল কলেজ হাসপাতাল ",
        "time": "প্রতি শনিবার, সোমবার ও বুধবার"
      },{
        "name": "ডাঃ মোঃ রাশেদ উল করিম",
        "spacalist": "শ্বাসকষ্ট, বাত-ব্যথা ও শিশুরোগের চিকিৎসক",
        "degree": "এমবিবিএস (চমেক), বিসিএস (স্বাস্থ্য), এফসিপিএস (শেষ পর্ব) ফিজিক্যাল মেডিসিন এন্ড রিহ্যাবিলিটেশন ",
        "post":"সহকারী রেজিষ্ট্রার-চট্টগ্রাম মেডিকেল কলেজ হাসপাতাল মেডিসিন",
        "time": "প্রতি শনি, রবি, মঙ্গল, বুধবার (বিকাল) শুক্রবার (সকাল)"
      },{
        "name": "ডাঃ সনজয় দে",
        "spacalist": "লিভার রোগ বিশেষজ্ঞ",
        "degree": "এমবিবিএস, এমডি (হেপাটোলজি) ",
        "post":"কনসালটেন্ট- চট্টগ্রাম মেডিকেল কলেজ হাসপাতাল",
        "time": "প্রতি শুক্রবার (বিকাল)"
      },{
        "name": "ডাঃ মোঃ নাজমুল হাসনাইন নওশাদ ",
        "spacalist": "বক্ষব্যাধি ও মেডিসিন বিশেষজ্ঞ ইন্টারভেনশনাল পালমোনোলজিষ্ট",
        "degree": "এমবিবিএস, বিসিএস (স্বাস্থ্য),এমডি (চেস্ট ডিজিজেজ), এফসিপিএস (আমেরিকা)",
        "post":"জাতীয় বক্ষব্যাধি ইনস্টিটিউট ও হাসপাতাল, (এক্স) ঢাকা কনসালটেন্ট, বক্ষব্যাধি ক্লিনিক, চট্টগ্রাম",
        "time": "প্রপ্রতি শুক্রবার (বিকাল)"
      },{
        "name": "ডাঃ মিসবাহুস সালেহীন",
        "spacalist": "চট্টগ্রাম মেডিকেল কলেজ হাসপাতাল মেডিসিন, বাত ব্যথা, হরমোন, ডায়াবেটিস,মানসিক রোগ বিশেষজ্ঞ",
        "degree": "এমবিবিএস, বিসিএস (স্বাস্থ্য),এমডি (চেস্ট ডিজিজেজ), এফসিপিএস (আমেরিকা)",
        "post":"এমবিবিএস, বিসিএস (স্বাস্থ্য), এমডি (মেডিসিন)",
        "time": "প্রতি রবিবার ও বৃহস্পতিবার (বিকাল)"
       },{
        "name": "ডাঃ শাকির উর রশিদ",
        "spacalist": "ব্যথা, প্যারালাইসিস,স্ট্রোক, স্পোর্টস ইনজুরি ও আঘাত জনিত ব্যথা বিশেষজ্ঞ",
        "degree": "এমবিবিএস, এফসিপিএস (ফিজিক্যাল মেডিসিম) ",
        "post":"চট্টগ্রাম মেডিকেল কলেজ হাসপাতাল",
        "time": "প্রতি সোমবার ও বৃহস্পতিবার (বিকাল)"
       },{
        "name": "ডাঃ রিয়াদ মোঃ মারজুক",
        "spacalist": "স্ট্রোক, প্যারালাইসিস, মগীরোগ, মাথা ব্যথা, কোমর ব্যথা,ঘাড় ব্যথা সহ সকল স্নায়ু রোগ বিশেষজ্ঞ",
        "degree": "এমবিবিএস, (চমেক), বিসিএস (স্বাস্থ্য),এমডি (নিউরোমেডিসিন) ",
        "post":"কনসালটেন্ট - নিউরোলজি - চট্টগ্রাম মেডিকেল কলেজ হাসপাতাল",
        "time": "প্রতি শুক্রবার (বিকাল)"
       },{
        "name": "ডাঃ রওনক জাহান",
        "spacalist": "স্ট্রোক, প্যারালাইসিস, মগীরোগ, মাথা ব্যথা, কোমর ব্যথা,ঘাড় ব্যথা সহ সকল স্নায়ু রোগ বিশেষজ্ঞ",
        "degree": "এমবিবিএস, বিসিএস (স্বাস্থ্য), ডিজিও (ঢাবি), এফসিপিএস (গাইনী) ডব্লিওএইচও ফেলো, থাইল্যান্ড",
        "post":"প্রসূতী, স্ত্রীরোগ বিশেষজ্ঞ ও সার্জন ",
        "time": "প্রতি শুক্রবার (বিকাল)"
       },{
        "name": "ডাঃ সুমন চৌধুরী",
        "spacalist": "বাত ব্যথা, হরমোন, ডায়াবেটিস, স্ট্রোক ও মেডিসিন বিশেষজ্ঞ",
        "degree": "এমবিবিএস, (চমেক), বিসিএস (স্বাস্থ্য) এফসিপিএস (মেডিসিন)",
        "post":"কনসালটেন্ট - মেডিসিন,চট্টগ্রাম মেডিকেল কলেজ হাসপাতাল ",
        "time": "প্রতি শনিবার ও বৃহস্পতিবার (বিকাল)"
       },{
        "name": "ডাঃ মর্তুজা কামাল মুর্শেদ ",
        "spacalist": "মেডিসিন, স্নায়ুরোগ, ডায়াবেটিস,বক্ষ্যব্যাধি ও বাতরোগ অভিজ্ঞ",
        "degree": "এমবিবিএস (সিএমসি), বিসিএস (স্বাস্থ্য) এমডি কোর্স (নিউরোলজি)",
        "post":"ন্যাশনাল ইনস্টিটিউট অব নিউরোসায়েন্সেস ও হাসপাতাল, ঢাকা ",
        "time": "প্রতি শুক্রবার"
       },{
        "name": "ডাঃ তাজদীনা হক খান ",
        "spacalist": " পাইলস, এনালফিশার,ফিস্টুলা, পিওথলির, পাথর ও হার্নিয়া রোগ বিশেষজ্ঞ ও সার্জন",
        "degree": "এমবিবিএস, বিসিএস (স্বাস্থ্য), এফসিপিএস (সার্জারী) রেজিস্ট্রার (কলোরেক্টাল সার্জারী)",
        "post":"চট্টগ্রাম মেডিকেল কলেজ হাসপা",
        "time": "প্রতি বৃহস্পতিবার (বিকাল) )"
       },{
        "name": "ডাঃ মোহাম্মদ মামুনুর রশীদ",
        "spacalist": " শিশু ও কিশোর রোগ বিশেষজ্ঞ",
        "degree": "এমবিবিএস, বিসিএস (স্বাস্থ্য), এফসিপিএস (শিশু স্বাস্থ্য - শেষ পর্ব)",
        "post":" উপজেলা স্বাস্থ্য ও পঃ পঃ কর্মকর্তা উপজেলা স্বাস্থ্য কমপ্লেক্স, আনোয়ারা,\n চট্টগ্রাম মেডিকেল কলেজ হাসপাতাল",
        "time": "প্রতি বৃহস্পতিবার (বিকাল) )"
       },{
        "name": "ডাঃ আব্দুল্লাহ্ আল মাহমুদ (সোহেল) ",
        "spacalist": " নাক, কান, গলা রোগ বিশেষজ্ঞ",
        "degree": "এমবিবিএস ডিএমইউ, ডিএলও এমএসএস (স্পীস ল্যাঙ্গুয়েজ প্যাথলজি)",
        "post":"সহকারী অধ্যাপক -বঙ্গবন্ধু মেমোরিয়াল হাসপাতাল (ইউএসটিসি)",
        "time": "প্রতি শনিবার, সোমবার ও বুধবার"
       },{
        "name": "ডাঃ আবিদা ইসলাম",
        "spacalist": "এলার্জি, চর্ম ও যৌন রোগ বিশেষজ্ঞ",
        "degree": "এমবিবিএস, বিসিএস (স্বাস্থ্য), এমডি (ডার্মাটোলজি) ",
        "post":"নবজাতক ও শিশুরোগ বিশেষজ্ঞ কনসালটেন্ট \n চট্টগ্রাম মা ও শিশু হাসপাতাল মেডিকেল কলেজ",
        "time": "প্রতি বৃহস্পতিবার (বিকাল)"
       },{
        "name": "ডাঃ বিজয় কুমার দত্ত",
        "spacalist": "মানসিক, যৌনরোগ, মাদকাসক্তি, চিকিৎসা এবং সাইকোথেরাথীতে বিশেষ অভিজ্ঞ সম্পন্ন",
        "degree": "বিবিএস, বিসিএস (স্বাস্থ্য), এমডি (সাইকিয়াট্রি) ",
        "post":"মনোরোগ বিশেষজ্ঞ- মনোরোগ বিদ্যা বিভাগ চট্টগ্রাম মেডিকেল কলেজ হাসপাতাল",
        "time": "প্রতি বৃহস্পতিবার (বিকাল)"
       },{
        "name": "ডাঃ শেখ কাওছার মাহমুদ",
        "spacalist": " বাত-ব্যথা, হাড় ভাঙ্গা, জোড় ও ট্রমা সার্জন",
        "degree": " এমবিবিএস, বিসিএস (স্বাস্থ্য), এমএস (অর্থোপেডিক এন্ড ট্রমাটোলজি) ",
        "post":"মনোরোগ বিশেষজ্ঞ- মনোরোগ বিদ্যা বিভাগ চট্টগ্রাম মেডিকেল কলেজ হাসপাতাল",
        "time": "প্রতি বৃহস্পতিবার (বিকাল)"
       },{
        "name": "ডাঃ আব্দুল মান্নান",
        "spacalist": "হৃদরোগ বিশেষজ্ঞ",
        "degree": " এমবিবিএস, বিসিএস (স্বাস্থ্য), এমএস (অর্থোপেডিক এন্ড ট্রমাটোলজি) ",
        "post":"কনসালটেন্ট- চট্টগ্রাম মেডিকেল কলেজ হাসপাতাল",
        "time": "প্রতি শুক্রবার (বিকাল) "
       },{
        "name": "ডাঃ সাহেদ আহমেদ ",
        "spacalist": "ডায়াবেটিস রোগ বিশেষজ্ঞ এবং মেডিসিন ও কিডনী রোগ চিকিৎসায় অভিজ্ঞ",
        "degree": "  এমবিবিএস, এমএসসি ডায়াবেটিস (লন্ডন) পিজিটি (মেডিসিন, কিডনী )",
        "post":"এক্স কনসালটেন্ট-চট্টগ্রাম ডায়াবেটিক জেনারেল হাসপাতাল",
        "time": "প্রতি বৃহস্পতিবার (বিকাল) "
       },{
        "name": "ডাঃ কামরুন নাহার ",
        "spacalist": "কসমেটিক লেজার সার্জন ",
        "degree": "এমবিবিএস, ডিডি, সিসিডি, পিজিটি (গাইনী এন্ড অবস),ফেলোশিপ ইন এসথেটিক মেডিসিন এন্ড লেজার এলার্জি",
        "post":" চর্ম ও যৌন রোগ বিশেষজ্ঞ",
        "time": "প্রতি রবিবার ও মঙ্গলবার"
       },{
        "name": "ডাঃ কামরুন নেছা বেগম (রোজী) ",
        "spacalist": "প্রসূতী, স্ত্রীরোগ বিশেষজ্ঞ ও সার্জন ",
        "degree": "এএমবিবিএস, বিসিএস (স্বাস্থ্য), এফসিপিএস (গাইনী), এমএস (থিসিস)",
        "post":"সহযোগী অধ্যাপক চট্টগ্রাম মেডিকেল কলেজ হাসপাতাল",
        "time": "প্রতি শনিবার (বিকাল)"
       },{
        "name": "অধ্যাপক ডাঃ এম আলমগীর চৌধুরী ",
        "spacalist": "কানে কম শুনা, বধির,এন্ডোস্কপিক সাইনাস,থাইরয়েড রোগীদের চিকিৎসা,সেলাই বিহীন টনসীল অপারেশন,কন্ঠস্বর পরিবর্তনের চিকিৎসা শিশুদের নাক কান ও গলা সমস্যার চিকিৎসা মুখগহ্বরের টিউমার অপসারণ ও চিকিৎসা নাকের হাড় বাঁকা রোগের চিকিৎসা",
        "degree": "এমবিবিএস, ডিএলও, এমএস (ইএনটি), এফআরসিএস (গ্লাসগো), এফএসিএস গোল্ড মেডালিষ্ট (বাংলাদেশ ও ইউএসএ)",
        "post":"অধ্যাপক ও বিভাগীয় প্রধান, ইএনটি আনোয়ার খান মর্ডাণ মেডিকেল কলেজ হাসপাতাল, ঢাকা",
        "time": "প্রতি শুক্রবার (বিকাল)"
       },
      {
        "name": "ডাঃ অপরুপ কান্তি দাশ ",
        "spacalist": "নবজাতক,শিশু ও কিশোর রোগ বিশেষজ্ঞ ",
        "degree": "এমবিবিএস, বিসিএস (স্বাস্থ্য), এফসিপিএস (শিশু স্বাস্থ্য)",
        "post":"সহযোগী অধ্যাপক চট্টগ্রাম মেডিকেল কলেজ হাসপাতাল",
        "time": "প্রতি শুক্রবার ও মঙ্গলবার"
       }
      
    ]
  }
]
